testkraken/__init__.py
testkraken/_version.py
testkraken/altair_plots.py
testkraken/cli.py
testkraken/container_generator.py
testkraken/testrunner.py
testkraken/workflowregtest.py
testkraken/dashboard_template/dashboard.js
testkraken/dashboard_template/index.html
testkraken/dashboard_template/results.csv
testkraken/dashboard_template/style.css
testkraken/testing_functions/__init__.py
testkraken/testing_functions/check_output.py
testkraken/testing_functions/stat_list.py
testkraken/testing_functions/test_afni_scan_data.py
testkraken/testing_functions/test_afni_scan_data_diff_fake.py
testkraken/testing_functions/test_afni_scan_headers.py
testkraken/testing_functions/test_arr_eq.py
testkraken/testing_functions/test_el_list_eq.py
testkraken/testing_functions/test_el_list_eq_tmp.py
testkraken/testing_functions/test_el_list_eq_tmp_noarray.py
testkraken/testing_functions/test_js_el_list_eq.py
testkraken/testing_functions/test_obj_eq.py
testkraken/testing_functions/test_rand_almosteq.py
testkraken/tests/__init__.py
testkraken/tests/test_afni.py
testkraken/tests/test_basic_examples.py
testkraken/tests/test_nfm.py
testkraken-0.1.5.dist-info/METADATA
testkraken-0.1.5.dist-info/WHEEL
testkraken-0.1.5.dist-info/entry_points.txt
testkraken-0.1.5.dist-info/top_level.txt
testkraken-0.1.5.dist-info/RECORD
